tests/__init__.py
tests/test_all.py
weichigong/__init__.py
weichigong-1.0.3.dist-info/LICENSE
weichigong-1.0.3.dist-info/METADATA
weichigong-1.0.3.dist-info/WHEEL
weichigong-1.0.3.dist-info/top_level.txt
weichigong-1.0.3.dist-info/RECORD
